{
  "type": "minecraft:barter",
  "pools": [
    {
      "rolls": 1,
      "entries": [
        {
          "type": "minecraft:item",
          "weight": 5,
          "functions": [
          ],
          "name": "minecraft:bone"
        },
        {
          "type": "minecraft:item",
          "weight": 5,
          "functions": [
          ],
          "name": "minecraft:gold_nugget"
        },
        {
          "type": "minecraft:item",
          "weight": 5,
          "functions": [
          ],
          "name": "minecraft:iron_nugget"
        },
        {
          "type": "minecraft:item",
          "weight": 5,
          "functions": [
          ],
          "name": "minecraft:string"
        },
        {
          "type": "minecraft:item",
          "weight": 1,
          "functions": [
          ],
          "name": "unusualprehistory:coty_fossil"
        },
        {
          "type": "minecraft:item",
          "weight": 1,
          "functions": [
          ],
          "name": "unusualprehistory:stetha_fossil"
        },
        {
          "type": "minecraft:item",
          "weight": 1,
          "functions": [
          ],
          "name": "unusualprehistory:anuro_fossil"
        },
        {
          "type": "minecraft:item",
          "weight": 1,
          "functions": [
          ],
          "name": "unusualprehistory:scau_fossil"
        }
      ]
    }
  ]
}