{
	"format_version": "1.8.0",
	"animations": {
		"animation.hyneria.swim_idle": {
			"loop": true,
			"animation_length": 8,
			"bones": {
				"Body": {
					"rotation": {
						"vector": [
							"-2.5*query.is_on_ground+math.sin(query.anim_time*45)*(5-2.5*query.is_on_ground)",
							"math.sin(query.anim_time*180)*(5-2.5*query.is_on_ground)",
							"math.sin(query.anim_time*180+120)*(-5+2.5*query.is_on_ground)"
						]
					},
					"position": {
						"vector": [
							"math.sin(query.anim_time*180+90)*(1-1*query.is_on_ground)",
							"3-2.5*query.is_on_ground+math.sin(query.anim_time*45-120)*(-1+1*query.is_on_ground)",
							0
						]
					}
				},
				"Head": {
					"rotation": {
						"vector": ["math.sin(query.anim_time*45-60)*-5", "math.sin(query.anim_time*180-30)*-5", "math.sin(query.anim_time*180+150)*5"]
					}
				},
				"TopFin2": {
					"rotation": {
						"vector": [0, "math.sin(query.anim_time*180+90)*-10", "math.sin(query.anim_time*180+180)*10"]
					}
				},
				"BottomFins": {
					"rotation": {
						"vector": [0, "math.sin(query.anim_time*180+90)*-10", "math.sin(query.anim_time*180+180)*-10"]
					}
				},
				"Fin1": {
					"rotation": {
						"vector": [
							"10+math.sin(query.anim_time*360+60)*(15-15*query.is_on_ground)",
							"math.sin(query.anim_time*360+30)*5",
							"-45*query.is_on_ground+math.sin(query.anim_time*360-60)*(10-7.5*query.is_on_ground)"
						]
					}
				},
				"Fin2": {
					"rotation": {
						"vector": [
							"10+math.sin(query.anim_time*360+60)*(15-15*query.is_on_ground)",
							"math.sin(query.anim_time*360+30)*-5",
							"45*query.is_on_ground+math.sin(query.anim_time*360-60)*(-10+7.5*query.is_on_ground)"
						]
					}
				},
				"BackFin1": {
					"rotation": {
						"vector": [
							"10+math.sin(query.anim_time*360+120)*(-15+15*query.is_on_ground)",
							"-20+math.sin(query.anim_time*360+90)*-5",
							"10-60*query.is_on_ground+math.sin(query.anim_time*360)*(-10+7.5*query.is_on_ground)"
						]
					}
				},
				"BackFin2": {
					"rotation": {
						"vector": [
							"10+math.sin(query.anim_time*360+120)*(-15+15*query.is_on_ground)",
							"20+math.sin(query.anim_time*360+90)*5",
							"-10+60*query.is_on_ground+math.sin(query.anim_time*360)*(10-7.5*query.is_on_ground)"
						]
					}
				},
				"TailBody": {
					"rotation": {
						"vector": [0, "math.sin(query.anim_time*180+90)*(-10+5*query.is_on_ground)", "math.sin(query.anim_time*180+210)*5"]
					}
				},
				"Tail": {
					"rotation": {
						"vector": [0, "math.sin(query.anim_time*180+30)*(-15+10*query.is_on_ground)", "math.sin(query.anim_time*180+150)*5"]
					}
				},
				"LowerJaw": {
					"rotation": {
						"vector": ["2.5+math.sin(query.anim_time*180)*2.5", 0, 0]
					}
				},
				"root": {
					"position": {
						"vector": [0, 0, 0]
					}
				}
			}
		},
		"animation.hyneria.swim": {
			"loop": true,
			"animation_length": 4,
			"bones": {
				"Body": {
					"rotation": {
						"vector": ["math.sin(query.anim_time*180)*2.5", "math.sin(query.anim_time*360+15)*7.5", "math.sin(query.anim_time*360+60)*-5"]
					},
					"position": {
						"vector": ["math.sin(query.anim_time*360+50)*2", "5+math.sin(query.anim_time*180-90)*-1", "math.sin(query.anim_time*90)*3"]
					}
				},
				"Head": {
					"rotation": {
						"vector": ["math.sin(query.anim_time*180-60)*-2.5", "math.sin(query.anim_time*360-15)*-7.5", "math.sin(query.anim_time*360)*5"]
					}
				},
				"TopJaw": {
					"rotation": {
						"vector": ["-2.5+math.sin(query.anim_time*90)*-2.5", 0, 0]
					}
				},
				"LowerJaw": {
					"rotation": {
						"vector": ["2.5+math.sin(query.anim_time*90)*2.5", 0, 0]
					}
				},
				"TopFin1": {
					"rotation": {
						"vector": [-10, 0, 0]
					}
				},
				"TopFin2": {
					"rotation": {
						"vector": [0, "math.sin(query.anim_time*360+60)*-10", "math.sin(query.anim_time*360+90)*-20"]
					}
				},
				"BottomFins": {
					"rotation": {
						"vector": [0, "math.sin(query.anim_time*360+60)*-10", "math.sin(query.anim_time*360+90)*20"]
					}
				},
				"Fin1": {
					"rotation": {
						"vector": ["math.sin(query.anim_time*1440)*2", "-30+math.sin(query.anim_time*360+60)*-7.5", "math.sin(query.anim_time*360+90)*5"]
					}
				},
				"Fin2": {
					"rotation": {
						"vector": ["math.sin(query.anim_time*1440)*-2", "30+math.sin(query.anim_time*360+60)*-7.5", "math.sin(query.anim_time*360+90)*5"]
					}
				},
				"BackFin1": {
					"rotation": {
						"vector": ["math.sin(query.anim_time*1440)*2", "-50+math.sin(query.anim_time*360+120)*-7.5", "math.sin(query.anim_time*360+120)*5"]
					}
				},
				"BackFin2": {
					"rotation": {
						"vector": ["math.sin(query.anim_time*1440)*-2", "50+math.sin(query.anim_time*360+120)*-7.5", "math.sin(query.anim_time*360+120)*5"]
					}
				},
				"TailBody": {
					"rotation": {
						"vector": ["math.sin(query.anim_time*180+60)*-2.5", "math.sin(query.anim_time*360+70)*-20", "math.sin(query.anim_time*360+60)*5"]
					}
				},
				"Tail": {
					"rotation": {
						"vector": [0, "math.sin(query.anim_time*360)*-20", "math.sin(query.anim_time*360)*5"]
					}
				}
			}
		},
		"animation.hyneria.swim_fast": {
			"loop": true,
			"animation_length": 4,
			"bones": {
				"Body": {
					"rotation": {
						"vector": [0, "math.sin(query.anim_time*720+15)*10", "math.sin(query.anim_time*720+60)*-5"]
					},
					"position": {
						"vector": ["math.sin(query.anim_time*720+60)*2", 5, "math.sin(query.anim_time*180)*3"]
					}
				},
				"Head": {
					"rotation": {
						"vector": [0, "math.sin(query.anim_time*720-15)*-7.5", "math.sin(query.anim_time*720)*5"]
					}
				},
				"TopFin1": {
					"rotation": {
						"vector": [-20, 0, 0]
					}
				},
				"TopFin2": {
					"rotation": {
						"vector": [-10, "math.sin(query.anim_time*720+60)*-10", "math.sin(query.anim_time*720+90)*-20"]
					}
				},
				"BottomFins": {
					"rotation": {
						"vector": [10, "math.sin(query.anim_time*720+60)*-10", "math.sin(query.anim_time*720+90)*20"]
					}
				},
				"Fin1": {
					"rotation": {
						"vector": ["30+math.sin(query.anim_time*1440)*2", "-60+math.sin(query.anim_time*720+60)*-7.5", "math.sin(query.anim_time*720+90)*5"]
					}
				},
				"Fin2": {
					"rotation": {
						"vector": ["30+math.sin(query.anim_time*1440)*-2", "60+math.sin(query.anim_time*720+60)*-7.5", "math.sin(query.anim_time*720+120)*5"]
					}
				},
				"BackFin1": {
					"rotation": {
						"vector": ["math.sin(query.anim_time*1440)*2", "-50+math.sin(query.anim_time*720+120)*-7.5", "math.sin(query.anim_time*720+120)*5"]
					}
				},
				"BackFin2": {
					"rotation": {
						"vector": ["math.sin(query.anim_time*1440)*-2", "50+math.sin(query.anim_time*720+120)*-7.5", "math.sin(query.anim_time*720+120)*5"]
					}
				},
				"TailBody": {
					"rotation": {
						"vector": [0, "math.sin(query.anim_time*720+90)*-25", "math.sin(query.anim_time*720+60)*5"]
					}
				},
				"Tail": {
					"rotation": {
						"vector": [0, "math.sin(query.anim_time*720+60)*-30", "math.sin(query.anim_time*720)*5"]
					}
				},
				"TopJaw": {
					"rotation": {
						"vector": ["-5+math.sin(query.anim_time*90)*5", 0, 0]
					}
				},
				"LowerJaw": {
					"rotation": {
						"vector": ["5+math.sin(query.anim_time*90)*-5", 0, 0]
					}
				}
			}
		},
		"animation.hyneria.idle": {
			"loop": true,
			"animation_length": 8,
			"bones": {
				"Body": {
					"rotation": {
						"vector": [
							"15-17.5*query.is_on_ground+math.sin(query.anim_time*180)*1.25*query.is_on_ground",
							"math.sin(query.anim_time*1440-60)*(2.5-2.5*query.is_on_ground)",
							"math.sin(query.anim_time*1440)*(1.25-1.25*query.is_on_ground)"
						]
					},
					"position": {
						"vector": [
							0,
							"10-10*query.is_on_ground+math.sin(query.anim_time*180-30)*-0.25*query.is_on_ground+math.sin(query.anim_time*180)*(0.5-0.5*query.is_on_ground)",
							0
						]
					}
				},
				"Head": {
					"rotation": {
						"vector": [
							"10-10*query.is_on_ground+math.sin(query.anim_time*180+90)*-2.5*query.is_on_ground",
							"math.sin(query.anim_time*1440)*(-2.5+2.5*query.is_on_ground)",
							"math.sin(query.anim_time*45)*5*query.is_on_ground+math.sin(query.anim_time*1440+60)*(-1.25+1.25*query.is_on_ground)"
						]
					}
				},
				"TopFin1": {
					"rotation": {
						"vector": [-20, 0, 0]
					}
				},
				"TopFin2": {
					"rotation": {
						"vector": [
							"-10+10*query.is_on_ground",
							"math.sin(query.anim_time*1440)*(-5+5*query.is_on_ground)",
							"math.sin(query.anim_time*1440+60)*(-5+5*query.is_on_ground)"
						]
					},
					"position": {
						"vector": [0, "-3*query.is_on_ground", 0]
					}
				},
				"BottomFins": {
					"rotation": {
						"vector": [
							"-15+15*query.is_on_ground",
							"math.sin(query.anim_time*1440)*(-5+5*query.is_on_ground)",
							"math.sin(query.anim_time*1440+60)*(5-5*query.is_on_ground)"
						]
					},
					"position": {
						"vector": [0, "4*query.is_on_ground", 0]
					}
				},
				"Fin1": {
					"rotation": {
						"vector": [
							"2.5*query.is_on_ground",
							"-10-10*query.is_on_ground+math.sin(query.anim_time*1440)*(-2.5+2.5*query.is_on_ground)",
							"-20-32.5*query.is_on_ground+math.sin(query.anim_time*180)*-2.5*query.is_on_ground+math.sin(query.anim_time*1440+60)*(-5+5*query.is_on_ground)"
						]
					},
					"position": {
						"vector": [0, "-2*query.is_on_ground", 0]
					}
				},
				"Fin2": {
					"rotation": {
						"vector": [
							"2.5*query.is_on_ground",
							"10+10*query.is_on_ground+math.sin(query.anim_time*1440)*(-2.5+2.5*query.is_on_ground)",
							"20+32.5*query.is_on_ground+math.sin(query.anim_time*180)*2.5*query.is_on_ground+math.sin(query.anim_time*1440+60)*(-5+5*query.is_on_ground)"
						]
					},
					"position": {
						"vector": [0, "-2*query.is_on_ground", 0]
					}
				},
				"BackFin1": {
					"rotation": {
						"vector": [
							"math.sin(query.anim_time*180-90)*2.5*query.is_on_ground",
							"-30+5*query.is_on_ground+math.sin(query.anim_time*1440+60)*(-2.5+2.5*query.is_on_ground)",
							"10-60*query.is_on_ground+math.sin(query.anim_time*180-60)*-2.5*query.is_on_ground+math.sin(query.anim_time*1440+120)*(-5+5*query.is_on_ground)"
						]
					}
				},
				"BackFin2": {
					"rotation": {
						"vector": [
							"math.sin(query.anim_time*180-90)*2.5*query.is_on_ground",
							"30-5*query.is_on_ground+math.sin(query.anim_time*1440+60)*(-2.5+2.5*query.is_on_ground)",
							"-10+60*query.is_on_ground+math.sin(query.anim_time*180-60)*2.5*query.is_on_ground+math.sin(query.anim_time*1440+120)*(-5+5*query.is_on_ground)"
						]
					}
				},
				"TailBody": {
					"rotation": {
						"vector": [
							"-10+math.sin(query.anim_time*180+60)*-2.5*query.is_on_ground",
							"10*query.is_on_ground+math.sin(query.anim_time*1440)*(-5+5*query.is_on_ground)",
							"45*query.is_on_ground+math.sin(query.anim_time*1440+60)*(-2.5+2.5*query.is_on_ground)"
						]
					}
				},
				"Tail": {
					"rotation": {
						"vector": [
							"-10+10*query.is_on_ground+math.sin(query.anim_time*180)*-2.5*query.is_on_ground",
							"math.sin(query.anim_time*1440-60)*(-10+10*query.is_on_ground)",
							"45*query.is_on_ground+math.sin(query.anim_time*1440)*(-2.5+2.5*query.is_on_ground)"
						]
					}
				},
				"TopJaw": {
					"rotation": {
						"vector": [0, 0, 0]
					}
				},
				"LowerJaw": {
					"rotation": {
						"vector": [
							"25-17.5*query.is_on_ground+math.sin(query.anim_time*180)*-2.5*query.is_on_ground+math.sin(query.anim_time*90)*-5*query.is_on_ground",
							0,
							0
						]
					}
				}
			}
		},
		"animation.hyneria.walk": {
			"loop": true,
			"animation_length": 2,
			"bones": {
				"Body": {
					"rotation": {
						"0.0": {
							"vector": [
								"15-15*query.is_on_ground",
								"math.sin(query.anim_time*180-90)*-5*query.is_on_ground+math.sin(query.anim_time*1440-60)*(2.5-2.5*query.is_on_ground)",
								"math.sin(query.anim_time*1440)*(1.25-1.25*query.is_on_ground)"
							]
						},
						"0.0417": {
							"vector": [
								"15-15.3*query.is_on_ground",
								"math.sin(query.anim_time*180-90)*-5*query.is_on_ground+math.sin(query.anim_time*1440-60)*(2.5-2.5*query.is_on_ground)",
								"math.sin(query.anim_time*1440)*(1.25-1.25*query.is_on_ground)"
							]
						},
						"0.0833": {
							"vector": [
								"15-15.9*query.is_on_ground",
								"math.sin(query.anim_time*180-90)*-5*query.is_on_ground+math.sin(query.anim_time*1440-60)*(2.5-2.5*query.is_on_ground)",
								"math.sin(query.anim_time*1440)*(1.25-1.25*query.is_on_ground)"
							]
						},
						"0.125": {
							"vector": [
								"15-16.5*query.is_on_ground",
								"math.sin(query.anim_time*180-90)*-5*query.is_on_ground+math.sin(query.anim_time*1440-60)*(2.5-2.5*query.is_on_ground)",
								"math.sin(query.anim_time*1440)*(1.25-1.25*query.is_on_ground)"
							]
						},
						"0.1667": {
							"vector": [
								"15-16.87*query.is_on_ground",
								"math.sin(query.anim_time*180-90)*-5*query.is_on_ground+math.sin(query.anim_time*1440-60)*(2.5-2.5*query.is_on_ground)",
								"math.sin(query.anim_time*1440)*(1.25-1.25*query.is_on_ground)"
							]
						},
						"0.2083": {
							"vector": [
								"15-17.13*query.is_on_ground",
								"math.sin(query.anim_time*180-90)*-5*query.is_on_ground+math.sin(query.anim_time*1440-60)*(2.5-2.5*query.is_on_ground)",
								"math.sin(query.anim_time*1440)*(1.25-1.25*query.is_on_ground)"
							]
						},
						"0.25": {
							"vector": [
								"15-17.2*query.is_on_ground",
								"math.sin(query.anim_time*180-90)*-5*query.is_on_ground+math.sin(query.anim_time*1440-60)*(2.5-2.5*query.is_on_ground)",
								"math.sin(query.anim_time*1440)*(1.25-1.25*query.is_on_ground)"
							]
						},
						"0.375": {
							"vector": [
								"15-17.2*query.is_on_ground",
								"math.sin(query.anim_time*180-90)*-5*query.is_on_ground+math.sin(query.anim_time*1440-60)*(2.5-2.5*query.is_on_ground)",
								"math.sin(query.anim_time*1440)*(1.25-1.25*query.is_on_ground)"
							]
						},
						"0.4167": {
							"vector": [
								"15-17.15*query.is_on_ground",
								"math.sin(query.anim_time*180-90)*-5*query.is_on_ground+math.sin(query.anim_time*1440-60)*(2.5-2.5*query.is_on_ground)",
								"math.sin(query.anim_time*1440)*(1.25-1.25*query.is_on_ground)"
							]
						},
						"0.4583": {
							"vector": [
								"15-17.05*query.is_on_ground",
								"math.sin(query.anim_time*180-90)*-5*query.is_on_ground+math.sin(query.anim_time*1440-60)*(2.5-2.5*query.is_on_ground)",
								"math.sin(query.anim_time*1440)*(1.25-1.25*query.is_on_ground)"
							]
						},
						"0.5": {
							"vector": [
								"15-16.76*query.is_on_ground",
								"math.sin(query.anim_time*180-90)*-5*query.is_on_ground+math.sin(query.anim_time*1440-60)*(2.5-2.5*query.is_on_ground)",
								"math.sin(query.anim_time*1440)*(1.25-1.25*query.is_on_ground)"
							]
						},
						"0.5417": {
							"vector": [
								"15-16.27*query.is_on_ground",
								"math.sin(query.anim_time*180-90)*-5*query.is_on_ground+math.sin(query.anim_time*1440-60)*(2.5-2.5*query.is_on_ground)",
								"math.sin(query.anim_time*1440)*(1.25-1.25*query.is_on_ground)"
							]
						},
						"0.5833": {
							"vector": [
								"15-15.78*query.is_on_ground",
								"math.sin(query.anim_time*180-90)*-5*query.is_on_ground+math.sin(query.anim_time*1440-60)*(2.5-2.5*query.is_on_ground)",
								"math.sin(query.anim_time*1440)*(1.25-1.25*query.is_on_ground)"
							]
						},
						"0.625": {
							"vector": [
								"15-15.34*query.is_on_ground",
								"math.sin(query.anim_time*180-90)*-5*query.is_on_ground+math.sin(query.anim_time*1440-60)*(2.5-2.5*query.is_on_ground)",
								"math.sin(query.anim_time*1440)*(1.25-1.25*query.is_on_ground)"
							]
						},
						"0.6667": {
							"vector": [
								"15-15.04*query.is_on_ground",
								"math.sin(query.anim_time*180-90)*-5*query.is_on_ground+math.sin(query.anim_time*1440-60)*(2.5-2.5*query.is_on_ground)",
								"math.sin(query.anim_time*1440)*(1.25-1.25*query.is_on_ground)"
							]
						},
						"0.7083": {
							"vector": [
								"15-14.78*query.is_on_ground",
								"math.sin(query.anim_time*180-90)*-5*query.is_on_ground+math.sin(query.anim_time*1440-60)*(2.5-2.5*query.is_on_ground)",
								"math.sin(query.anim_time*1440)*(1.25-1.25*query.is_on_ground)"
							]
						},
						"0.75": {
							"vector": [
								"15-14.63*query.is_on_ground",
								"math.sin(query.anim_time*180-90)*-5*query.is_on_ground+math.sin(query.anim_time*1440-60)*(2.5-2.5*query.is_on_ground)",
								"math.sin(query.anim_time*1440)*(1.25-1.25*query.is_on_ground)"
							]
						},
						"0.7917": {
							"vector": [
								"15-14.51*query.is_on_ground",
								"math.sin(query.anim_time*180-90)*-5*query.is_on_ground+math.sin(query.anim_time*1440-60)*(2.5-2.5*query.is_on_ground)",
								"math.sin(query.anim_time*1440)*(1.25-1.25*query.is_on_ground)"
							]
						},
						"0.8333": {
							"vector": [
								"15-14.48*query.is_on_ground",
								"math.sin(query.anim_time*180-90)*-5*query.is_on_ground+math.sin(query.anim_time*1440-60)*(2.5-2.5*query.is_on_ground)",
								"math.sin(query.anim_time*1440)*(1.25-1.25*query.is_on_ground)"
							]
						},
						"0.875": {
							"vector": [
								"15-14.51*query.is_on_ground",
								"math.sin(query.anim_time*180-90)*-5*query.is_on_ground+math.sin(query.anim_time*1440-60)*(2.5-2.5*query.is_on_ground)",
								"math.sin(query.anim_time*1440)*(1.25-1.25*query.is_on_ground)"
							]
						},
						"0.9167": {
							"vector": [
								"15-14.59*query.is_on_ground",
								"math.sin(query.anim_time*180-90)*-5*query.is_on_ground+math.sin(query.anim_time*1440-60)*(2.5-2.5*query.is_on_ground)",
								"math.sin(query.anim_time*1440)*(1.25-1.25*query.is_on_ground)"
							]
						},
						"0.9583": {
							"vector": [
								"15-14.77*query.is_on_ground",
								"math.sin(query.anim_time*180-90)*-5*query.is_on_ground+math.sin(query.anim_time*1440-60)*(2.5-2.5*query.is_on_ground)",
								"math.sin(query.anim_time*1440)*(1.25-1.25*query.is_on_ground)"
							]
						},
						"1.0": {
							"vector": [
								"15-15*query.is_on_ground",
								"math.sin(query.anim_time*180-90)*-5*query.is_on_ground+math.sin(query.anim_time*1440-60)*(2.5-2.5*query.is_on_ground)",
								"math.sin(query.anim_time*1440)*(1.25-1.25*query.is_on_ground)"
							]
						},
						"1.0417": {
							"vector": [
								"15-15.3*query.is_on_ground",
								"math.sin(query.anim_time*180-90)*-5*query.is_on_ground+math.sin(query.anim_time*1440-60)*(2.5-2.5*query.is_on_ground)",
								"math.sin(query.anim_time*1440)*(1.25-1.25*query.is_on_ground)"
							]
						},
						"1.0833": {
							"vector": [
								"15-15.9*query.is_on_ground",
								"math.sin(query.anim_time*180-90)*-5*query.is_on_ground+math.sin(query.anim_time*1440-60)*(2.5-2.5*query.is_on_ground)",
								"math.sin(query.anim_time*1440)*(1.25-1.25*query.is_on_ground)"
							]
						},
						"1.125": {
							"vector": [
								"15-16.5*query.is_on_ground",
								"math.sin(query.anim_time*180-90)*-5*query.is_on_ground+math.sin(query.anim_time*1440-60)*(2.5-2.5*query.is_on_ground)",
								"math.sin(query.anim_time*1440)*(1.25-1.25*query.is_on_ground)"
							]
						},
						"1.1667": {
							"vector": [
								"15-16.87*query.is_on_ground",
								"math.sin(query.anim_time*180-90)*-5*query.is_on_ground+math.sin(query.anim_time*1440-60)*(2.5-2.5*query.is_on_ground)",
								"math.sin(query.anim_time*1440)*(1.25-1.25*query.is_on_ground)"
							]
						},
						"1.2083": {
							"vector": [
								"15-17.13*query.is_on_ground",
								"math.sin(query.anim_time*180-90)*-5*query.is_on_ground+math.sin(query.anim_time*1440-60)*(2.5-2.5*query.is_on_ground)",
								"math.sin(query.anim_time*1440)*(1.25-1.25*query.is_on_ground)"
							]
						},
						"1.25": {
							"vector": [
								"15-17.2*query.is_on_ground",
								"math.sin(query.anim_time*180-90)*-5*query.is_on_ground+math.sin(query.anim_time*1440-60)*(2.5-2.5*query.is_on_ground)",
								"math.sin(query.anim_time*1440)*(1.25-1.25*query.is_on_ground)"
							]
						},
						"1.375": {
							"vector": [
								"15-17.2*query.is_on_ground",
								"math.sin(query.anim_time*180-90)*-5*query.is_on_ground+math.sin(query.anim_time*1440-60)*(2.5-2.5*query.is_on_ground)",
								"math.sin(query.anim_time*1440)*(1.25-1.25*query.is_on_ground)"
							]
						},
						"1.4167": {
							"vector": [
								"15-17.15*query.is_on_ground",
								"math.sin(query.anim_time*180-90)*-5*query.is_on_ground+math.sin(query.anim_time*1440-60)*(2.5-2.5*query.is_on_ground)",
								"math.sin(query.anim_time*1440)*(1.25-1.25*query.is_on_ground)"
							]
						},
						"1.4583": {
							"vector": [
								"15-17.05*query.is_on_ground",
								"math.sin(query.anim_time*180-90)*-5*query.is_on_ground+math.sin(query.anim_time*1440-60)*(2.5-2.5*query.is_on_ground)",
								"math.sin(query.anim_time*1440)*(1.25-1.25*query.is_on_ground)"
							]
						},
						"1.5": {
							"vector": [
								"15-16.76*query.is_on_ground",
								"math.sin(query.anim_time*180-90)*-5*query.is_on_ground+math.sin(query.anim_time*1440-60)*(2.5-2.5*query.is_on_ground)",
								"math.sin(query.anim_time*1440)*(1.25-1.25*query.is_on_ground)"
							]
						},
						"1.5417": {
							"vector": [
								"15-16.27*query.is_on_ground",
								"math.sin(query.anim_time*180-90)*-5*query.is_on_ground+math.sin(query.anim_time*1440-60)*(2.5-2.5*query.is_on_ground)",
								"math.sin(query.anim_time*1440)*(1.25-1.25*query.is_on_ground)"
							]
						},
						"1.5833": {
							"vector": [
								"15-15.78*query.is_on_ground",
								"math.sin(query.anim_time*180-90)*-5*query.is_on_ground+math.sin(query.anim_time*1440-60)*(2.5-2.5*query.is_on_ground)",
								"math.sin(query.anim_time*1440)*(1.25-1.25*query.is_on_ground)"
							]
						},
						"1.625": {
							"vector": [
								"15-15.34*query.is_on_ground",
								"math.sin(query.anim_time*180-90)*-5*query.is_on_ground+math.sin(query.anim_time*1440-60)*(2.5-2.5*query.is_on_ground)",
								"math.sin(query.anim_time*1440)*(1.25-1.25*query.is_on_ground)"
							]
						},
						"1.6667": {
							"vector": [
								"15-15.04*query.is_on_ground",
								"math.sin(query.anim_time*180-90)*-5*query.is_on_ground+math.sin(query.anim_time*1440-60)*(2.5-2.5*query.is_on_ground)",
								"math.sin(query.anim_time*1440)*(1.25-1.25*query.is_on_ground)"
							]
						},
						"1.7083": {
							"vector": [
								"15-14.78*query.is_on_ground",
								"math.sin(query.anim_time*180-90)*-5*query.is_on_ground+math.sin(query.anim_time*1440-60)*(2.5-2.5*query.is_on_ground)",
								"math.sin(query.anim_time*1440)*(1.25-1.25*query.is_on_ground)"
							]
						},
						"1.75": {
							"vector": [
								"15-14.63*query.is_on_ground",
								"math.sin(query.anim_time*180-90)*-5*query.is_on_ground+math.sin(query.anim_time*1440-60)*(2.5-2.5*query.is_on_ground)",
								"math.sin(query.anim_time*1440)*(1.25-1.25*query.is_on_ground)"
							]
						},
						"1.7917": {
							"vector": [
								"15-14.51*query.is_on_ground",
								"math.sin(query.anim_time*180-90)*-5*query.is_on_ground+math.sin(query.anim_time*1440-60)*(2.5-2.5*query.is_on_ground)",
								"math.sin(query.anim_time*1440)*(1.25-1.25*query.is_on_ground)"
							]
						},
						"1.8333": {
							"vector": [
								"15-14.48*query.is_on_ground",
								"math.sin(query.anim_time*180-90)*-5*query.is_on_ground+math.sin(query.anim_time*1440-60)*(2.5-2.5*query.is_on_ground)",
								"math.sin(query.anim_time*1440)*(1.25-1.25*query.is_on_ground)"
							]
						},
						"1.875": {
							"vector": [
								"15-14.51*query.is_on_ground",
								"math.sin(query.anim_time*180-90)*-5*query.is_on_ground+math.sin(query.anim_time*1440-60)*(2.5-2.5*query.is_on_ground)",
								"math.sin(query.anim_time*1440)*(1.25-1.25*query.is_on_ground)"
							]
						},
						"1.9167": {
							"vector": [
								"15-14.59*query.is_on_ground",
								"math.sin(query.anim_time*180-90)*-5*query.is_on_ground+math.sin(query.anim_time*1440-60)*(2.5-2.5*query.is_on_ground)",
								"math.sin(query.anim_time*1440)*(1.25-1.25*query.is_on_ground)"
							]
						},
						"1.9583": {
							"vector": [
								"15-14.77*query.is_on_ground",
								"math.sin(query.anim_time*180-90)*-5*query.is_on_ground+math.sin(query.anim_time*1440-60)*(2.5-2.5*query.is_on_ground)",
								"math.sin(query.anim_time*1440)*(1.25-1.25*query.is_on_ground)"
							]
						},
						"2.0": {
							"vector": [
								"15-15*query.is_on_ground",
								"math.sin(query.anim_time*180-90)*-5*query.is_on_ground+math.sin(query.anim_time*1440-60)*(2.5-2.5*query.is_on_ground)",
								"math.sin(query.anim_time*1440)*(1.25-1.25*query.is_on_ground)"
							]
						}
					},
					"position": {
						"vector": [
							"math.sin(query.anim_time*180+60)*-1*query.is_on_ground",
							"10-10*query.is_on_ground+math.sin(query.anim_time*180)*(0.5-0.5*query.is_on_ground)",
							"math.sin(query.anim_time*360-60)*-0.5*query.is_on_ground"
						]
					}
				},
				"Head": {
					"rotation": {
						"vector": [
							"10-10*query.is_on_ground+math.sin(query.anim_time*180)*5*query.is_on_ground",
							"math.sin(query.anim_time*1440)*(-2.5+2.5*query.is_on_ground)",
							"math.sin(query.anim_time*1440+60)*(-1.25+1.25*query.is_on_ground)"
						]
					}
				},
				"LowerJaw": {
					"rotation": {
						"vector": ["25-20*query.is_on_ground+math.sin(query.anim_time*360)*2.5*query.is_on_ground+math.sin(query.anim_time*180)*2.5*query.is_on_ground", 0, 0]
					}
				},
				"TopFin1": {
					"rotation": {
						"vector": ["-20+math.sin(query.anim_time*180+120)*5*query.is_on_ground", 0, 0]
					}
				},
				"TopFin2": {
					"rotation": {
						"vector": [
							"-10+math.sin(query.anim_time*180+90)*10*query.is_on_ground",
							"math.sin(query.anim_time*1440)*(-5+5*query.is_on_ground)",
							"math.sin(query.anim_time*1440+60)*(-5+5*query.is_on_ground)"
						]
					},
					"position": {
						"vector": [0, "-1*query.is_on_ground", 0]
					}
				},
				"BottomFins": {
					"rotation": {
						"vector": [
							"-15+15*query.is_on_ground",
							"math.sin(query.anim_time*1440)*(-5+5*query.is_on_ground)",
							"math.sin(query.anim_time*1440+60)*(5-5*query.is_on_ground)"
						]
					},
					"position": {
						"vector": [0, "3*query.is_on_ground", 0]
					}
				},
				"Fin1": {
					"rotation": {
						"0.0": {
							"vector": [
								"5*query.is_on_ground",
								"-10+65*query.is_on_ground+math.sin(query.anim_time*1440)*(-2.5+2.5*query.is_on_ground)",
								"-20-32.5*query.is_on_ground+math.sin(query.anim_time*1440+60)*(-5+5*query.is_on_ground)"
							]
						},
						"0.25": {
							"vector": [
								"5*query.is_on_ground",
								"-10+35*query.is_on_ground+math.sin(query.anim_time*1440)*(-2.5+2.5*query.is_on_ground)",
								"-20-35*query.is_on_ground+math.sin(query.anim_time*1440+60)*(-5+5*query.is_on_ground)"
							]
						},
						"0.5": {
							"vector": [
								"5*query.is_on_ground",
								"-10-5*query.is_on_ground+math.sin(query.anim_time*1440)*(-2.5+2.5*query.is_on_ground)",
								"-20-35*query.is_on_ground+math.sin(query.anim_time*1440+60)*(-5+5*query.is_on_ground)"
							]
						},
						"0.75": {
							"vector": [
								"10*query.is_on_ground",
								"-10-27.5*query.is_on_ground+math.sin(query.anim_time*1440)*(-2.5+2.5*query.is_on_ground)",
								"-20-35*query.is_on_ground+math.sin(query.anim_time*1440+60)*(-5+5*query.is_on_ground)"
							]
						},
						"1.0": {
							"vector": [
								"-10*query.is_on_ground",
								"-10-40*query.is_on_ground+math.sin(query.anim_time*1440)*(-2.5+2.5*query.is_on_ground)",
								"-20-37.5*query.is_on_ground+math.sin(query.anim_time*1440+60)*(-5+5*query.is_on_ground)"
							]
						},
						"1.25": {
							"vector": [
								"-10*query.is_on_ground",
								"-10+5*query.is_on_ground+math.sin(query.anim_time*1440)*(-2.5+2.5*query.is_on_ground)",
								"-20-47.5*query.is_on_ground+math.sin(query.anim_time*1440+60)*(-5+5*query.is_on_ground)"
							]
						},
						"1.5": {
							"vector": [
								"-10*query.is_on_ground",
								"-10+45*query.is_on_ground+math.sin(query.anim_time*1440)*(-2.5+2.5*query.is_on_ground)",
								"-20-50*query.is_on_ground+math.sin(query.anim_time*1440+60)*(-5+5*query.is_on_ground)"
							]
						},
						"1.75": {
							"vector": [
								"5*query.is_on_ground",
								"-10+70*query.is_on_ground+math.sin(query.anim_time*1440)*(-2.5+2.5*query.is_on_ground)",
								"-20-32.5*query.is_on_ground+math.sin(query.anim_time*1440+60)*(-5+5*query.is_on_ground)"
							]
						},
						"2.0": {
							"vector": [
								"5*query.is_on_ground",
								"-10+65*query.is_on_ground+math.sin(query.anim_time*1440)*(-2.5+2.5*query.is_on_ground)",
								"-20-32.5*query.is_on_ground+math.sin(query.anim_time*1440+60)*(-5+5*query.is_on_ground)"
							]
						}
					},
					"position": {
						"0.0": {
							"vector": [0, "-2*query.is_on_ground", "-1*query.is_on_ground"]
						},
						"0.25": {
							"vector": [0, "-2*query.is_on_ground", "-0.5*query.is_on_ground"]
						},
						"0.5": {
							"vector": [0, "-2*query.is_on_ground", 0]
						},
						"0.75": {
							"vector": [0, "-2*query.is_on_ground", "1*query.is_on_ground"]
						},
						"1.0": {
							"vector": [0, "-2*query.is_on_ground", "1*query.is_on_ground"]
						},
						"1.25": {
							"vector": [0, "-2*query.is_on_ground", 0]
						},
						"1.5": {
							"vector": [0, "-2*query.is_on_ground", "-1*query.is_on_ground"]
						},
						"1.75": {
							"vector": [0, "-2*query.is_on_ground", "-1*query.is_on_ground"]
						},
						"2.0": {
							"vector": [0, "-2*query.is_on_ground", "-1*query.is_on_ground"]
						}
					}
				},
				"Fin2": {
					"rotation": {
						"0.0": {
							"vector": [
								"-10*query.is_on_ground",
								"10+40*query.is_on_ground+math.sin(query.anim_time*1440)*(-2.5+2.5*query.is_on_ground)",
								"20+37.5*query.is_on_ground+math.sin(query.anim_time*1440+60)*(-5+5*query.is_on_ground)"
							]
						},
						"0.25": {
							"vector": [
								"-10*query.is_on_ground",
								"10-5*query.is_on_ground+math.sin(query.anim_time*1440)*(-2.5+2.5*query.is_on_ground)",
								"20+47.5*query.is_on_ground+math.sin(query.anim_time*1440+60)*(-5+5*query.is_on_ground)"
							]
						},
						"0.5": {
							"vector": [
								"-10*query.is_on_ground",
								"10-45*query.is_on_ground+math.sin(query.anim_time*1440)*(-2.5+2.5*query.is_on_ground)",
								"20+50*query.is_on_ground+math.sin(query.anim_time*1440+60)*(-5+5*query.is_on_ground)"
							]
						},
						"0.75": {
							"vector": [
								"5*query.is_on_ground",
								"10-70*query.is_on_ground+math.sin(query.anim_time*1440)*(-2.5+2.5*query.is_on_ground)",
								"20+32.5*query.is_on_ground+math.sin(query.anim_time*1440+60)*(-5+5*query.is_on_ground)"
							]
						},
						"1.0": {
							"vector": [
								"5*query.is_on_ground",
								"10-65*query.is_on_ground+math.sin(query.anim_time*1440)*(-2.5+2.5*query.is_on_ground)",
								"20+32.5*query.is_on_ground+math.sin(query.anim_time*1440+60)*(-5+5*query.is_on_ground)"
							]
						},
						"1.25": {
							"vector": [
								"5*query.is_on_ground",
								"10-35*query.is_on_ground+math.sin(query.anim_time*1440)*(-2.5+2.5*query.is_on_ground)",
								"20+35*query.is_on_ground+math.sin(query.anim_time*1440+60)*(-5+5*query.is_on_ground)"
							]
						},
						"1.5": {
							"vector": [
								"5*query.is_on_ground",
								"10+5*query.is_on_ground+math.sin(query.anim_time*1440)*(-2.5+2.5*query.is_on_ground)",
								"20+35*query.is_on_ground+math.sin(query.anim_time*1440+60)*(-5+5*query.is_on_ground)"
							]
						},
						"1.75": {
							"vector": [
								"10*query.is_on_ground",
								"10+27.5*query.is_on_ground+math.sin(query.anim_time*1440)*(-2.5+2.5*query.is_on_ground)",
								"20+35*query.is_on_ground+math.sin(query.anim_time*1440+60)*(-5+5*query.is_on_ground)"
							]
						},
						"2.0": {
							"vector": [
								"-10*query.is_on_ground",
								"10+40*query.is_on_ground+math.sin(query.anim_time*1440)*(-2.5+2.5*query.is_on_ground)",
								"20+37.5*query.is_on_ground+math.sin(query.anim_time*1440+60)*(-5+5*query.is_on_ground)"
							]
						}
					},
					"position": {
						"0.0": {
							"vector": [0, "-2*query.is_on_ground", "1*query.is_on_ground"]
						},
						"0.25": {
							"vector": [0, "-2*query.is_on_ground", 0]
						},
						"0.5": {
							"vector": [0, "-2*query.is_on_ground", "-1*query.is_on_ground"]
						},
						"0.75": {
							"vector": [0, "-2*query.is_on_ground", "-1*query.is_on_ground"]
						},
						"1.0": {
							"vector": [0, "-2*query.is_on_ground", "-1*query.is_on_ground"]
						},
						"1.25": {
							"vector": [0, "-2*query.is_on_ground", "-0.5*query.is_on_ground"]
						},
						"1.5": {
							"vector": [0, "-2*query.is_on_ground", 0]
						},
						"1.75": {
							"vector": [0, "-2*query.is_on_ground", "1*query.is_on_ground"]
						},
						"2.0": {
							"vector": [0, "-2*query.is_on_ground", "1*query.is_on_ground"]
						}
					}
				},
				"BackFin1": {
					"rotation": {
						"0.0": {
							"vector": [
								"10*query.is_on_ground",
								"-30-7.5*query.is_on_ground+math.sin(query.anim_time*1440+60)*(-2.5+2.5*query.is_on_ground)",
								"10-57.5*query.is_on_ground+math.sin(query.anim_time*1440+120)*(-5+5*query.is_on_ground)"
							]
						},
						"0.25": {
							"vector": [
								"-10*query.is_on_ground",
								"-30-20*query.is_on_ground+math.sin(query.anim_time*1440+60)*(-2.5+2.5*query.is_on_ground)",
								"10-62.5*query.is_on_ground+math.sin(query.anim_time*1440+120)*(-5+5*query.is_on_ground)"
							]
						},
						"0.5": {
							"vector": [
								"-10*query.is_on_ground",
								"-30+25*query.is_on_ground+math.sin(query.anim_time*1440+60)*(-2.5+2.5*query.is_on_ground)",
								"10-67.5*query.is_on_ground+math.sin(query.anim_time*1440+120)*(-5+5*query.is_on_ground)"
							]
						},
						"0.75": {
							"vector": [
								"-10*query.is_on_ground",
								"-30+45*query.is_on_ground+math.sin(query.anim_time*1440+60)*(-2.5+2.5*query.is_on_ground)",
								"10-70*query.is_on_ground+math.sin(query.anim_time*1440+120)*(-5+5*query.is_on_ground)"
							]
						},
						"1.0": {
							"vector": [
								"5*query.is_on_ground",
								"-30+70*query.is_on_ground+math.sin(query.anim_time*1440+60)*(-2.5+2.5*query.is_on_ground)",
								"10-52.5*query.is_on_ground+math.sin(query.anim_time*1440+120)*(-5+5*query.is_on_ground)"
							]
						},
						"1.25": {
							"vector": [
								"5*query.is_on_ground",
								"-30+60*query.is_on_ground+math.sin(query.anim_time*1440+60)*(-2.5+2.5*query.is_on_ground)",
								"10-55*query.is_on_ground+math.sin(query.anim_time*1440+120)*(-5+5*query.is_on_ground)"
							]
						},
						"1.5": {
							"vector": [
								"5*query.is_on_ground",
								"-30+42.5*query.is_on_ground+math.sin(query.anim_time*1440+60)*(-2.5+2.5*query.is_on_ground)",
								"10-55*query.is_on_ground+math.sin(query.anim_time*1440+120)*(-5+5*query.is_on_ground)"
							]
						},
						"1.75": {
							"vector": [
								"5*query.is_on_ground",
								"-30+10*query.is_on_ground+math.sin(query.anim_time*1440+60)*(-2.5+2.5*query.is_on_ground)",
								"10-57.5*query.is_on_ground+math.sin(query.anim_time*1440+120)*(-5+5*query.is_on_ground)"
							]
						},
						"2.0": {
							"vector": [
								"10*query.is_on_ground",
								"-30-7.5*query.is_on_ground+math.sin(query.anim_time*1440+60)*(-2.5+2.5*query.is_on_ground)",
								"10-57.5*query.is_on_ground+math.sin(query.anim_time*1440+120)*(-5+5*query.is_on_ground)"
							]
						}
					},
					"position": {
						"0.0": {
							"vector": [0, 0, "1*query.is_on_ground"]
						},
						"0.25": {
							"vector": [0, 0, "1*query.is_on_ground"]
						},
						"0.5": {
							"vector": [0, 0, 0]
						},
						"0.75": {
							"vector": [0, 0, "-1*query.is_on_ground"]
						},
						"1.0": {
							"vector": [0, 0, "-1*query.is_on_ground"]
						},
						"1.25": {
							"vector": [0, 0, "-1*query.is_on_ground"]
						},
						"1.5": {
							"vector": [0, 0, "-0.5*query.is_on_ground"]
						},
						"1.75": {
							"vector": [0, 0, 0]
						},
						"2.0": {
							"vector": [0, 0, "1*query.is_on_ground"]
						}
					}
				},
				"BackFin2": {
					"rotation": {
						"0.0": {
							"vector": [
								"5*query.is_on_ground",
								"30-70*query.is_on_ground+math.sin(query.anim_time*1440+60)*(-2.5+2.5*query.is_on_ground)",
								"-10+52.5*query.is_on_ground+math.sin(query.anim_time*1440+120)*(-5+5*query.is_on_ground)"
							]
						},
						"0.25": {
							"vector": [
								"5*query.is_on_ground",
								"30-60*query.is_on_ground+math.sin(query.anim_time*1440+60)*(-2.5+2.5*query.is_on_ground)",
								"-10+55*query.is_on_ground+math.sin(query.anim_time*1440+120)*(-5+5*query.is_on_ground)"
							]
						},
						"0.5": {
							"vector": [
								"5*query.is_on_ground",
								"30-42.5*query.is_on_ground+math.sin(query.anim_time*1440+60)*(-2.5+2.5*query.is_on_ground)",
								"-10+55*query.is_on_ground+math.sin(query.anim_time*1440+120)*(-5+5*query.is_on_ground)"
							]
						},
						"0.75": {
							"vector": [
								"5*query.is_on_ground",
								"30-10*query.is_on_ground+math.sin(query.anim_time*1440+60)*(-2.5+2.5*query.is_on_ground)",
								"-10+57.5*query.is_on_ground+math.sin(query.anim_time*1440+120)*(-5+5*query.is_on_ground)"
							]
						},
						"1.0": {
							"vector": [
								"10*query.is_on_ground",
								"30+7.5*query.is_on_ground+math.sin(query.anim_time*1440+60)*(-2.5+2.5*query.is_on_ground)",
								"-10+57.5*query.is_on_ground+math.sin(query.anim_time*1440+120)*(-5+5*query.is_on_ground)"
							]
						},
						"1.25": {
							"vector": [
								"-10*query.is_on_ground",
								"30+20*query.is_on_ground+math.sin(query.anim_time*1440+60)*(-2.5+2.5*query.is_on_ground)",
								"-10+62.5*query.is_on_ground+math.sin(query.anim_time*1440+120)*(-5+5*query.is_on_ground)"
							]
						},
						"1.5": {
							"vector": [
								"-10*query.is_on_ground",
								"30-25*query.is_on_ground+math.sin(query.anim_time*1440+60)*(-2.5+2.5*query.is_on_ground)",
								"-10+67.5*query.is_on_ground+math.sin(query.anim_time*1440+120)*(-5+5*query.is_on_ground)"
							]
						},
						"1.75": {
							"vector": [
								"-10*query.is_on_ground",
								"30-45*query.is_on_ground+math.sin(query.anim_time*1440+60)*(-2.5+2.5*query.is_on_ground)",
								"-10+70*query.is_on_ground+math.sin(query.anim_time*1440+120)*(-5+5*query.is_on_ground)"
							]
						},
						"2.0": {
							"vector": [
								"5*query.is_on_ground",
								"30-70*query.is_on_ground+math.sin(query.anim_time*1440+60)*(-2.5+2.5*query.is_on_ground)",
								"-10+52.5*query.is_on_ground+math.sin(query.anim_time*1440+120)*(-5+5*query.is_on_ground)"
							]
						}
					},
					"position": {
						"0.0": {
							"vector": [0, 0, "-1*query.is_on_ground"]
						},
						"0.25": {
							"vector": [0, 0, "-1*query.is_on_ground"]
						},
						"0.5": {
							"vector": [0, 0, "-0.5*query.is_on_ground"]
						},
						"0.75": {
							"vector": [0, 0, 0]
						},
						"1.0": {
							"vector": [0, 0, "1*query.is_on_ground"]
						},
						"1.25": {
							"vector": [0, 0, "1*query.is_on_ground"]
						},
						"1.5": {
							"vector": [0, 0, 0]
						},
						"1.75": {
							"vector": [0, 0, "-1*query.is_on_ground"]
						},
						"2.0": {
							"vector": [0, 0, "-1*query.is_on_ground"]
						}
					}
				},
				"TailBody": {
					"rotation": {
						"vector": [
							"-10+math.sin(query.anim_time*360+60)*5*query.is_on_ground",
							"10*query.is_on_ground+math.sin(query.anim_time*360+60)*-5*query.is_on_ground+math.sin(query.anim_time*1440)*(-5+5*query.is_on_ground)",
							"45*query.is_on_ground+math.sin(query.anim_time*1440+60)*(-2.5+2.5*query.is_on_ground)"
						]
					}
				},
				"Tail": {
					"rotation": {
						"vector": [
							"-10+10*query.is_on_ground",
							"-10*query.is_on_ground+math.sin(query.anim_time*360)*-10*query.is_on_ground+math.sin(query.anim_time*1440-60)*(-10+10*query.is_on_ground)",
							"45*query.is_on_ground+math.sin(query.anim_time*1440)*(-2.5+2.5*query.is_on_ground)"
						]
					}
				}
			}
		},
		"animation.hyneria.jump": {
			"loop": true,
			"animation_length": 2,
			"bones": {
				"Body": {
					"rotation": {
						"vector": [-15, "math.sin(query.anim_time*1440-60)*2.5", "math.sin(query.anim_time*1440)*1.25"]
					},
					"position": {
						"vector": [0, "10+math.sin(query.anim_time*180)*0.5", 0]
					}
				},
				"Head": {
					"rotation": {
						"vector": [10, "math.sin(query.anim_time*1440)*-2.5", "math.sin(query.anim_time*1440+60)*-1.25"]
					}
				},
				"TopFin2": {
					"rotation": {
						"vector": [-10, "math.sin(query.anim_time*1440)*-5", "math.sin(query.anim_time*1440+60)*-5"]
					}
				},
				"BottomFins": {
					"rotation": {
						"vector": [-15, "math.sin(query.anim_time*1440)*-5", "math.sin(query.anim_time*1440+60)*5"]
					}
				},
				"Fin1": {
					"rotation": {
						"vector": [0, "-10+math.sin(query.anim_time*1440)*-2.5", "-20+math.sin(query.anim_time*1440+60)*-5"]
					}
				},
				"Fin2": {
					"rotation": {
						"vector": [0, "10+math.sin(query.anim_time*1440)*-2.5", "20+math.sin(query.anim_time*1440+60)*-5"]
					}
				},
				"BackFin1": {
					"rotation": {
						"vector": [0, "-30+math.sin(query.anim_time*1440+60)*-2.5", "10+math.sin(query.anim_time*1440+120)*-5"]
					}
				},
				"BackFin2": {
					"rotation": {
						"vector": [0, "30+math.sin(query.anim_time*1440+60)*-2.5", "-10+math.sin(query.anim_time*1440+120)*-5"]
					}
				},
				"TailBody": {
					"rotation": {
						"vector": [-10, "math.sin(query.anim_time*1440)*-5", "math.sin(query.anim_time*1440+60)*-2.5"]
					}
				},
				"Tail": {
					"rotation": {
						"vector": [-10, "math.sin(query.anim_time*1440-60)*-10", "math.sin(query.anim_time*1440)*-2.5"]
					}
				},
				"LowerJaw": {
					"rotation": {
						"vector": [25, 0, 0]
					}
				}
			}
		},
		"animation.hyneria.bask": {
			"loop": true,
			"animation_length": 8,
			"bones": {
				"Body": {
					"rotation": {
						"vector": [
							"15-17.5*query.is_on_ground+math.sin(query.anim_time*180)*1*query.is_on_ground",
							"math.sin(query.anim_time*1440-60)*(2.5-2.5*query.is_on_ground)",
							"math.sin(query.anim_time*1440)*(1.25-1.25*query.is_on_ground)"
						]
					},
					"position": {
						"vector": [
							0,
							"10-10*query.is_on_ground+math.sin(query.anim_time*180-30)*-0.1*query.is_on_ground+math.sin(query.anim_time*180)*(0.5-0.5*query.is_on_ground)",
							0
						]
					}
				},
				"Head": {
					"rotation": {
						"vector": [
							"10-40*query.is_on_ground+math.sin(query.anim_time*180+90)*-1*query.is_on_ground",
							"math.sin(query.anim_time*1440)*(-2.5+2.5*query.is_on_ground)",
							"math.sin(query.anim_time*45)*2.5*query.is_on_ground+math.sin(query.anim_time*1440+60)*(-1.25+1.25*query.is_on_ground)"
						]
					}
				},
				"TopFin1": {
					"rotation": {
						"vector": [-20, 0, 0]
					}
				},
				"TopFin2": {
					"rotation": {
						"vector": [
							"-10+10*query.is_on_ground",
							"math.sin(query.anim_time*1440)*(-5+5*query.is_on_ground)",
							"math.sin(query.anim_time*1440+60)*(-5+5*query.is_on_ground)"
						]
					},
					"position": {
						"vector": [0, "-3*query.is_on_ground", 0]
					}
				},
				"BottomFins": {
					"rotation": {
						"vector": [
							"-15+15*query.is_on_ground",
							"math.sin(query.anim_time*1440)*(-5+5*query.is_on_ground)",
							"math.sin(query.anim_time*1440+60)*(5-5*query.is_on_ground)"
						]
					},
					"position": {
						"vector": [0, "4*query.is_on_ground", 0]
					}
				},
				"Fin1": {
					"rotation": {
						"vector": [
							"2.5*query.is_on_ground",
							"-10-10*query.is_on_ground+math.sin(query.anim_time*1440)*(-2.5+2.5*query.is_on_ground)",
							"-20-32.5*query.is_on_ground+math.sin(query.anim_time*180)*-2.5*query.is_on_ground+math.sin(query.anim_time*1440+60)*(-5+5*query.is_on_ground)"
						]
					},
					"position": {
						"vector": [0, "-2*query.is_on_ground", 0]
					}
				},
				"Fin2": {
					"rotation": {
						"vector": [
							"2.5*query.is_on_ground",
							"10+10*query.is_on_ground+math.sin(query.anim_time*1440)*(-2.5+2.5*query.is_on_ground)",
							"20+32.5*query.is_on_ground+math.sin(query.anim_time*180)*2.5*query.is_on_ground+math.sin(query.anim_time*1440+60)*(-5+5*query.is_on_ground)"
						]
					},
					"position": {
						"vector": [0, "-2*query.is_on_ground", 0]
					}
				},
				"BackFin1": {
					"rotation": {
						"vector": [
							"math.sin(query.anim_time*180-90)*2.5*query.is_on_ground",
							"-30+5*query.is_on_ground+math.sin(query.anim_time*1440+60)*(-2.5+2.5*query.is_on_ground)",
							"10-60*query.is_on_ground+math.sin(query.anim_time*180-60)*-2.5*query.is_on_ground+math.sin(query.anim_time*1440+120)*(-5+5*query.is_on_ground)"
						]
					}
				},
				"BackFin2": {
					"rotation": {
						"vector": [
							"math.sin(query.anim_time*180-90)*2.5*query.is_on_ground",
							"30-5*query.is_on_ground+math.sin(query.anim_time*1440+60)*(-2.5+2.5*query.is_on_ground)",
							"-10+60*query.is_on_ground+math.sin(query.anim_time*180-60)*2.5*query.is_on_ground+math.sin(query.anim_time*1440+120)*(-5+5*query.is_on_ground)"
						]
					}
				},
				"TailBody": {
					"rotation": {
						"vector": [
							"-10+math.sin(query.anim_time*180+60)*-2.5*query.is_on_ground",
							"10*query.is_on_ground+math.sin(query.anim_time*1440)*(-5+5*query.is_on_ground)",
							"45*query.is_on_ground+math.sin(query.anim_time*1440+60)*(-2.5+2.5*query.is_on_ground)"
						]
					}
				},
				"Tail": {
					"rotation": {
						"vector": [
							"-10+10*query.is_on_ground+math.sin(query.anim_time*180)*-2.5*query.is_on_ground",
							"math.sin(query.anim_time*1440-60)*(-10+10*query.is_on_ground)",
							"45*query.is_on_ground+math.sin(query.anim_time*1440)*(-2.5+2.5*query.is_on_ground)"
						]
					}
				},
				"TopJaw": {
					"rotation": {
						"vector": [0, 0, 0]
					}
				},
				"LowerJaw": {
					"rotation": {
						"vector": ["25+30*query.is_on_ground+math.sin(query.anim_time*90)*-1*query.is_on_ground", 0, 0]
					}
				}
			}
		},
		"animation.hyneria.attack_blend": {
			"animation_length": 0.5,
			"bones": {
				"Body_B": {
					"rotation": {
						"0.0": {
							"vector": [0, 0, "math.sin(query.anim_time*180/0.13)*10"]
						},
						"0.125": {
							"vector": [0, 0, 5]
						},
						"0.2083": {
							"vector": [0, "math.sin(query.anim_time*1440)*5", "math.sin(query.anim_time*180/0.5-30)*-10+math.sin(query.anim_time*1440-60)*-5"]
						},
						"0.5": {
							"vector": [0, 0, 0]
						}
					},
					"position": {
						"0.0": {
							"vector": [0, 0, "math.sin(query.anim_time*180/0.13)*(2+5*query.is_in_water)"]
						},
						"0.125": {
							"vector": [0, 0, "-3-5*query.is_in_water"]
						},
						"0.5": {
							"vector": [0, 0, 0]
						}
					}
				},
				"Head_B": {
					"rotation": {
						"0.0": {
							"vector": [0, 0, 0]
						},
						"0.125": {
							"vector": [0, 0, 5]
						},
						"0.2083": {
							"vector": [0, 0, -10]
						},
						"0.5": {
							"vector": [0, 0, 0]
						}
					}
				},
				"TopJaw_B": {
					"rotation": {
						"0.0": {
							"vector": ["math.sin(query.anim_time*180/0.13)*-30", 0, 0]
						},
						"0.125": {
							"vector": ["math.sin(query.anim_time*180/0.21-30)*-30", 0, 0]
						},
						"0.2083": {
							"vector": [1, 0, 0]
						},
						"0.5": {
							"vector": [0, 0, 0]
						}
					}
				},
				"LowerJaw_B": {
					"rotation": {
						"0.0": {
							"vector": ["math.sin(query.anim_time*180/0.13)*30", 0, 0]
						},
						"0.125": {
							"vector": ["math.sin(query.anim_time*180/0.21-30)*30", 0, 0]
						},
						"0.2083": {
							"vector": [-1, 0, 0]
						},
						"0.5": {
							"vector": [0, 0, 0]
						}
					}
				},
				"Fin1_B": {
					"rotation": {
						"0.0": {
							"vector": [0, 0, "math.sin(query.anim_time*180/0.13)*-10"]
						},
						"0.125": {
							"vector": [0, 0, -5]
						},
						"0.2083": {
							"vector": [0, "math.sin(query.anim_time*1440)*-5", "math.sin(query.anim_time*180/0.5-30)*20+math.sin(query.anim_time*1440-60)*5"]
						},
						"0.5": {
							"vector": [0, 0, 0]
						}
					}
				},
				"Fin2_B": {
					"rotation": {
						"0.0": {
							"vector": [0, 0, "math.sin(query.anim_time*180/0.13)*-10"]
						},
						"0.125": {
							"vector": [0, 0, -5]
						},
						"0.2083": {
							"vector": [0, "math.sin(query.anim_time*1440)*-5", "math.sin(query.anim_time*180/0.5-30)*20+math.sin(query.anim_time*1440-60)*5"]
						},
						"0.5": {
							"vector": [0, 0, 0]
						}
					}
				},
				"BackFin1_B": {
					"rotation": {
						"0.0": {
							"vector": [0, 0, "math.sin(query.anim_time*180/0.13)*-10"]
						},
						"0.125": {
							"vector": [0, 0, -5]
						},
						"0.2083": {
							"vector": [0, "math.sin(query.anim_time*1440)*-5", "math.sin(query.anim_time*180/0.5-30)*20+math.sin(query.anim_time*1440-60)*5"]
						},
						"0.5": {
							"vector": [0, 0, 0]
						}
					}
				},
				"BackFin2_B": {
					"rotation": {
						"0.0": {
							"vector": [0, 0, "math.sin(query.anim_time*180/0.13)*-10"]
						},
						"0.125": {
							"vector": [0, 0, -5]
						},
						"0.2083": {
							"vector": [0, "math.sin(query.anim_time*1440)*-5", "math.sin(query.anim_time*180/0.5-30)*20+math.sin(query.anim_time*1440-60)*5"]
						},
						"0.5": {
							"vector": [0, 0, 0]
						}
					}
				},
				"TailBody_B": {
					"rotation": {
						"0.0": {
							"vector": [0, 0, 0]
						},
						"0.2083": {
							"vector": [0, "math.sin(query.anim_time*1440+60)*-10", "math.sin(query.anim_time*1440)*10"]
						},
						"0.5": {
							"vector": [0, 0, 0]
						}
					}
				},
				"Tail_B": {
					"rotation": {
						"0.0": {
							"vector": [0, 0, 0]
						},
						"0.2083": {
							"vector": [0, "math.sin(query.anim_time*1440+30)*-15", "math.sin(query.anim_time*1440-30)*15"]
						},
						"0.5": {
							"vector": [0, 0, 0]
						}
					}
				}
			}
		},
		"animation.hyneria.yawn_blend": {
			"animation_length": 3,
			"bones": {
				"TopJaw_B": {
					"rotation": {
						"0.0": {
							"vector": ["math.sin(query.anim_time*180/0.5)*10", 0, 0]
						},
						"0.5": {
							"vector": ["math.sin(query.anim_time*180/0.75)*-10", 0, 0]
						},
						"0.75": {
							"vector": [1, 0, 0]
						},
						"1.0": {
							"vector": [0, 0, 0]
						},
						"2.0": {
							"vector": ["math.sin(query.anim_time*180/2.5-30)*-10", 0, 0]
						},
						"3.0": {
							"vector": [0, 0, 0]
						}
					}
				},
				"LowerJaw_B": {
					"rotation": {
						"0.0": {
							"vector": ["math.sin(query.anim_time*180/0.5)*10", 0, 0]
						},
						"0.5": {
							"vector": ["math.sin(query.anim_time*180/0.75)*30", 0, 0]
						},
						"0.75": {
							"vector": [-1, 0, 0]
						},
						"1.0": {
							"vector": [0, 0, 0]
						},
						"2.0": {
							"vector": ["30+math.sin(query.anim_time*180/2.5+30)*30", 0, 0]
						},
						"3.0": {
							"vector": [0, 0, 0]
						}
					}
				}
			}
		}
	},
	"geckolib_format_version": 2
}