{
	"format_version": "1.8.0",
	"animations": {
		"animation.kimmeridgebrachypteraeschnidium.hover": {
			"loop": true,
			"animation_length": 8,
			"bones": {
				"Body": {
					"rotation": {
						"vector": [
							"-30+math.sin(query.anim_time*720+60)*-2.5+math.sin(query.anim_time*45+60)*-10",
							"math.sin(query.anim_time*90+60)*-10",
							"math.sin(query.anim_time*90+60)*10"
						]
					},
					"position": {
						"vector": [
							"math.sin(query.anim_time*90)*2",
							"5+math.sin(query.anim_time*720)*0.5+math.sin(query.anim_time*45-90)*2",
							"math.sin(query.anim_time*45)*2"
						]
					}
				},
				"Butt": {
					"rotation": {
						"vector": ["math.sin(query.anim_time*720+120)*2.5", 0, 0]
					}
				},
				"Head": {
					"rotation": {
						"vector": [
							"30+math.sin(query.anim_time*720+60)*2.5+math.sin(query.anim_time*45+60)*10",
							"math.sin(query.anim_time*90+60)*10",
							"math.sin(query.anim_time*90+60)*-10"
						]
					}
				},
				"FrontWingLeft": {
					"rotation": {
						"vector": ["math.sin(query.anim_time*1440-120)*-30", "-30+math.sin(query.anim_time*1440-120)*20", "-10+math.sin(query.anim_time*1440)*20"]
					}
				},
				"BackWingLeft": {
					"rotation": {
						"vector": ["math.sin(query.anim_time*1440-60)*30", "10+math.sin(query.anim_time*1440)*-10", "math.sin(query.anim_time*1440+60)*-20"]
					}
				},
				"FrontArmLeft": {
					"rotation": {
						"vector": ["107.5+math.sin(query.anim_time*360)*5", 0, 10]
					},
					"scale": {
						"vector": [0.8, 0.8, 0.8]
					}
				},
				"MiddleLegLeft": {
					"rotation": {
						"vector": ["90+math.sin(query.anim_time*360-240)*5", 10, 30]
					},
					"scale": {
						"vector": [0.8, 0.8, 0.8]
					}
				},
				"FrontWingRight": {
					"rotation": {
						"vector": ["math.sin(query.anim_time*1440-120)*-30", "30+math.sin(query.anim_time*1440-120)*-20", "10+math.sin(query.anim_time*1440)*-20"]
					}
				},
				"BackWingRight": {
					"rotation": {
						"vector": ["math.sin(query.anim_time*1440-60)*30", "-10+math.sin(query.anim_time*1440)*10", "math.sin(query.anim_time*1440+60)*20"]
					}
				},
				"FrontArmRight": {
					"rotation": {
						"vector": ["107.5+math.sin(query.anim_time*360-60)*5", 0, -10]
					},
					"scale": {
						"vector": [0.8, 0.8, 0.8]
					}
				},
				"BackLegLeft": {
					"rotation": {
						"vector": ["90+math.sin(query.anim_time*360-120)*-5", 0, -145]
					},
					"scale": {
						"vector": [0.8, 0.8, 0.8]
					}
				},
				"MiddleLegRight": {
					"rotation": {
						"vector": ["90+math.sin(query.anim_time*360-300)*5", -10, -30]
					},
					"scale": {
						"vector": [0.8, 0.8, 0.8]
					}
				},
				"BackLegRight": {
					"rotation": {
						"vector": ["90+math.sin(query.anim_time*360-180)*-5", 0, 145]
					},
					"scale": {
						"vector": [0.8, 0.8, 0.8]
					}
				},
				"root": {
					"position": {
						"vector": [0, 0, 0]
					}
				}
			}
		},
		"animation.kimmeridgebrachypteraeschnidium.fly": {
			"loop": true,
			"animation_length": 8,
			"bones": {
				"Body": {
					"rotation": ["math.sin(query.anim_time*720+60)*-2.5", 0, "math.sin(query.anim_time*45)*5"],
					"position": [0, "math.sin(query.anim_time*720)*0.5", "-2+math.sin(query.anim_time*45)*2"]
				},
				"Butt": {
					"rotation": ["math.sin(query.anim_time*720+120)*2.5", 0, 0]
				},
				"Head": {
					"rotation": ["math.sin(query.anim_time*720+60)*2.5", 0, "math.sin(query.anim_time*45)*-5"]
				},
				"FrontWingLeft": {
					"rotation": ["math.sin(query.anim_time*1440-120)*-30", "-30+math.sin(query.anim_time*1440+60)*10", "math.sin(query.anim_time*1440)*30"],
					"position": [1, 0, 0]
				},
				"BackWingLeft": {
					"rotation": ["math.sin(query.anim_time*1440-60)*30", "20+math.sin(query.anim_time*1440+120)*-10", "-10+math.sin(query.anim_time*1440+60)*-30"],
					"position": [1, 0, 0]
				},
				"FrontArmLeft": {
					"rotation": ["107.5+math.sin(query.anim_time*360)*5", 0, 10],
					"scale": 0.8
				},
				"MiddleLegLeft": {
					"rotation": ["90+math.sin(query.anim_time*360-240)*5", 10, 30],
					"scale": 0.8
				},
				"FrontWingRight": {
					"rotation": ["math.sin(query.anim_time*1440-120)*-30", "30+math.sin(query.anim_time*1440+60)*-10", "math.sin(query.anim_time*1440)*-30"],
					"position": [-1, 0, 0]
				},
				"BackWingRight": {
					"rotation": ["math.sin(query.anim_time*1440-60)*30", "-20+math.sin(query.anim_time*1440+120)*10", "10+math.sin(query.anim_time*1440+60)*30"],
					"position": [-1, 0, 0]
				},
				"FrontArmRight": {
					"rotation": ["107.5+math.sin(query.anim_time*360-60)*5", 0, -10],
					"scale": 0.8
				},
				"BackLegLeft": {
					"rotation": ["90+math.sin(query.anim_time*360-120)*-5", 0, -145],
					"scale": 0.8
				},
				"MiddleLegRight": {
					"rotation": ["90+math.sin(query.anim_time*360-300)*5", -10, -30],
					"scale": 0.8
				},
				"BackLegRight": {
					"rotation": ["90+math.sin(query.anim_time*360-180)*-5", 0, 145],
					"scale": 0.8
				}
			}
		},
		"animation.kimmeridgebrachypteraeschnidium.idle1": {
			"loop": true,
			"animation_length": 8,
			"bones": {
				"Body": {
					"rotation": ["math.sin(query.anim_time*180)*2.5", 0, 0],
					"position": [0, -0.25, 0]
				},
				"Butt": {
					"rotation": ["math.sin(query.anim_time*180+60)*-2.5", 0, 0]
				},
				"Head": {
					"rotation": {
						"0.0": [0, 0, 0],
						"0.9167": [0, 0, 0],
						"1.0": [-20, 0, 20],
						"1.9167": [-20, 0, 20],
						"2.0": [-20, 0, -20],
						"3.9167": [-20, 0, -20],
						"4.0": [20, 0, 0],
						"4.9167": [20, 0, 0],
						"5.0": [20, 0, -20],
						"5.9167": [20, 0, -20],
						"6.0": [20, 0, 20],
						"7.9167": [20, 0, 20],
						"8.0": [0, 0, 0]
					}
				},
				"FrontWingLeft": {
					"rotation": {
						"0.0": [-10, -60, "-10+math.sin(query.anim_time*90)*5"],
						"2.8333": [-10, -60, "-10+math.sin(query.anim_time*90)*5"],
						"3.0": ["math.sin(query.anim_time*1440*2-120)*-10", "-30+math.sin(query.anim_time*1440*2+60)*5", "math.sin(query.anim_time*1440*2)*10"],
						"3.5": ["math.sin(query.anim_time*1440*2-120)*-10", "-30+math.sin(query.anim_time*1440*2+60)*5", "math.sin(query.anim_time*1440*2)*10"],
						"3.6667": [-10, -60, "-10+math.sin(query.anim_time*90)*5"],
						"6.8333": [-10, -60, "-10+math.sin(query.anim_time*90)*5"],
						"7.0": ["math.sin(query.anim_time*1440*2-120)*-10", "-30+math.sin(query.anim_time*1440*2+60)*5", "math.sin(query.anim_time*1440*2)*10"],
						"7.5": ["math.sin(query.anim_time*1440*2-120)*-10", "-30+math.sin(query.anim_time*1440*2+60)*5", "math.sin(query.anim_time*1440*2)*10"],
						"7.6667": [-10, -60, "-10+math.sin(query.anim_time*90)*5"]
					}
				},
				"BackWingLeft": {
					"rotation": {
						"0.0": [10, -10, "-10+math.sin(query.anim_time*90-90)*5"],
						"2.8333": [10, -10, "-10+math.sin(query.anim_time*90-90)*5"],
						"3.0": ["math.sin(query.anim_time*1440*2-60)*10", "20+math.sin(query.anim_time*1440*2+120)*-5", "-10+math.sin(query.anim_time*1440*2+60)*-10"],
						"3.5": ["math.sin(query.anim_time*1440*2-60)*10", "20+math.sin(query.anim_time*1440*2+120)*-5", "-10+math.sin(query.anim_time*1440*2+60)*-10"],
						"3.6667": [10, -10, "-10+math.sin(query.anim_time*90-90)*5"],
						"6.8333": [10, -10, "-10+math.sin(query.anim_time*90-90)*5"],
						"7.0": ["math.sin(query.anim_time*1440*2-60)*10", "20+math.sin(query.anim_time*1440*2+120)*-5", "-10+math.sin(query.anim_time*1440*2+60)*-10"],
						"7.5": ["math.sin(query.anim_time*1440*2-60)*10", "20+math.sin(query.anim_time*1440*2+120)*-5", "-10+math.sin(query.anim_time*1440*2+60)*-10"],
						"7.6667": [10, -10, "-10+math.sin(query.anim_time*90-90)*5"]
					}
				},
				"FrontArmLeft": {
					"rotation": ["5+math.sin(query.anim_time*180)*-2.5", 15, -25]
				},
				"MiddleLegLeft": {
					"rotation": ["-15+math.sin(query.anim_time*180)*-2.5", 15, "math.sin(query.anim_time*180)*-2.5"]
				},
				"FrontWingRight": {
					"rotation": {
						"0.0": [-10, 60, "10+math.sin(query.anim_time*90)*-5"],
						"2.8333": [-10, 60, "10+math.sin(query.anim_time*90)*-5"],
						"3.0": ["math.sin(query.anim_time*1440*2-120)*-10", "30+math.sin(query.anim_time*1440*2+60)*-5", "math.sin(query.anim_time*1440*2)*-10"],
						"3.5": ["math.sin(query.anim_time*1440*2-120)*-10", "30+math.sin(query.anim_time*1440*2+60)*-5", "math.sin(query.anim_time*1440*2)*-10"],
						"3.6667": [-10, 60, "10+math.sin(query.anim_time*90)*-5"],
						"6.8333": [-10, 60, "10+math.sin(query.anim_time*90)*-5"],
						"7.0": ["math.sin(query.anim_time*1440*2-120)*-10", "30+math.sin(query.anim_time*1440*2+60)*-5", "math.sin(query.anim_time*1440*2)*-10"],
						"7.5": ["math.sin(query.anim_time*1440*2-120)*-10", "30+math.sin(query.anim_time*1440*2+60)*-5", "math.sin(query.anim_time*1440*2)*-10"],
						"7.6667": [-10, 60, "10+math.sin(query.anim_time*90)*-5"]
					}
				},
				"BackWingRight": {
					"rotation": {
						"0.0": [10, 10, "10+math.sin(query.anim_time*90-90)*-5"],
						"2.8333": [10, 10, "10+math.sin(query.anim_time*90-90)*-5"],
						"3.0": ["math.sin(query.anim_time*1440*2-60)*10", "-20+math.sin(query.anim_time*1440*2+120)*5", "10+math.sin(query.anim_time*1440*2+60)*10"],
						"3.5": ["math.sin(query.anim_time*1440*2-60)*10", "-20+math.sin(query.anim_time*1440*2+120)*5", "10+math.sin(query.anim_time*1440*2+60)*10"],
						"3.6667": [10, 10, "10+math.sin(query.anim_time*90-90)*-5"],
						"6.8333": [10, 10, "10+math.sin(query.anim_time*90-90)*-5"],
						"7.0": ["math.sin(query.anim_time*1440*2-60)*10", "-20+math.sin(query.anim_time*1440*2+120)*5", "10+math.sin(query.anim_time*1440*2+60)*10"],
						"7.5": ["math.sin(query.anim_time*1440*2-60)*10", "-20+math.sin(query.anim_time*1440*2+120)*5", "10+math.sin(query.anim_time*1440*2+60)*10"],
						"7.6667": [10, 10, "10+math.sin(query.anim_time*90-90)*-5"]
					}
				},
				"FrontArmRight": {
					"rotation": ["5+math.sin(query.anim_time*180)*-2.5", -15, 25]
				},
				"BackLegLeft": {
					"rotation": ["15+math.sin(query.anim_time*180)*-2.5", -20, "math.sin(query.anim_time*180)*2.5"]
				},
				"MiddleLegRight": {
					"rotation": ["-15+math.sin(query.anim_time*180)*-2.5", -15, "math.sin(query.anim_time*180)*2.5"]
				},
				"BackLegRight": {
					"rotation": ["15+math.sin(query.anim_time*180)*-2.5", 20, "math.sin(query.anim_time*180)*-2.5"]
				}
			}
		},
		"animation.kimmeridgebrachypteraeschnidium.idle2": {
			"loop": true,
			"animation_length": 8,
			"bones": {
				"Body": {
					"rotation": ["-10+math.sin(query.anim_time*180)*2.5", 0, 0],
					"position": [0, "0.95+math.sin(query.anim_time*180)*-0.1", 0]
				},
				"Butt": {
					"rotation": ["math.sin(query.anim_time*180+60)*-2.5", 0, 0]
				},
				"Head": {
					"rotation": {
						"0.0": [0, 0, 0],
						"0.9167": [0, 0, 0],
						"1.0": [-20, 0, 20],
						"1.9167": [-20, 0, 20],
						"2.0": [-20, 0, -20],
						"3.9167": [-20, 0, -20],
						"4.0": [20, 0, 0],
						"4.9167": [20, 0, 0],
						"5.0": [20, 0, -20],
						"5.9167": [20, 0, -20],
						"6.0": [20, 0, 20],
						"7.9167": [20, 0, 20],
						"8.0": [0, 0, 0]
					}
				},
				"FrontWingLeft": {
					"rotation": {
						"0.0": [-10, -60, "-60+math.sin(query.anim_time*90)*5"],
						"2.8333": [-10, -60, "-60+math.sin(query.anim_time*90)*5"],
						"3.0": ["math.sin(query.anim_time*1440*2-120)*-10", "-30+math.sin(query.anim_time*1440*2+60)*5", "math.sin(query.anim_time*1440*2)*10"],
						"3.5": ["math.sin(query.anim_time*1440*2-120)*-10", "-30+math.sin(query.anim_time*1440*2+60)*5", "math.sin(query.anim_time*1440*2)*10"],
						"3.6667": [-10, -60, "-60+math.sin(query.anim_time*90)*5"],
						"6.8333": [-10, -60, "-60+math.sin(query.anim_time*90)*5"],
						"7.0": ["math.sin(query.anim_time*1440*2-120)*-10", "-30+math.sin(query.anim_time*1440*2+60)*5", "math.sin(query.anim_time*1440*2)*10"],
						"7.5": ["math.sin(query.anim_time*1440*2-120)*-10", "-30+math.sin(query.anim_time*1440*2+60)*5", "math.sin(query.anim_time*1440*2)*10"],
						"7.6667": [-10, -60, "-60+math.sin(query.anim_time*90)*5"]
					}
				},
				"BackWingLeft": {
					"rotation": {
						"0.0": [10, -10, "-60+math.sin(query.anim_time*90-90)*5"],
						"2.8333": [10, -10, "-60+math.sin(query.anim_time*90-90)*5"],
						"3.0": ["math.sin(query.anim_time*1440*2-60)*10", "20+math.sin(query.anim_time*1440*2+120)*-5", "-10+math.sin(query.anim_time*1440*2+60)*-10"],
						"3.5": ["math.sin(query.anim_time*1440*2-60)*10", "20+math.sin(query.anim_time*1440*2+120)*-5", "-10+math.sin(query.anim_time*1440*2+60)*-10"],
						"3.6667": [10, -10, "-60+math.sin(query.anim_time*90-90)*5"],
						"6.8333": [10, -10, "-60+math.sin(query.anim_time*90-90)*5"],
						"7.0": ["math.sin(query.anim_time*1440*2-60)*10", "20+math.sin(query.anim_time*1440*2+120)*-5", "-10+math.sin(query.anim_time*1440*2+60)*-10"],
						"7.5": ["math.sin(query.anim_time*1440*2-60)*10", "20+math.sin(query.anim_time*1440*2+120)*-5", "-10+math.sin(query.anim_time*1440*2+60)*-10"],
						"7.6667": [10, -10, "-60+math.sin(query.anim_time*90-90)*5"]
					},
					"position": [0.5, -1, 0]
				},
				"FrontArmLeft": {
					"rotation": ["math.sin(query.anim_time*720)*-5", 10, 0]
				},
				"MiddleLegLeft": {
					"rotation": ["10+math.sin(query.anim_time*180)*-2.5", 0, 40]
				},
				"FrontWingRight": {
					"rotation": {
						"0.0": [-10, 60, "60+math.sin(query.anim_time*90)*-5"],
						"2.8333": [-10, 60, "60+math.sin(query.anim_time*90)*-5"],
						"3.0": ["math.sin(query.anim_time*1440*2-120)*-10", "30+math.sin(query.anim_time*1440*2+60)*-5", "math.sin(query.anim_time*1440*2)*-10"],
						"3.5": ["math.sin(query.anim_time*1440*2-120)*-10", "30+math.sin(query.anim_time*1440*2+60)*-5", "math.sin(query.anim_time*1440*2)*-10"],
						"3.6667": [-10, 60, "60+math.sin(query.anim_time*90)*-5"],
						"6.8333": [-10, 60, "60+math.sin(query.anim_time*90)*-5"],
						"7.0": ["math.sin(query.anim_time*1440*2-120)*-10", "30+math.sin(query.anim_time*1440*2+60)*-5", "math.sin(query.anim_time*1440*2)*-10"],
						"7.5": ["math.sin(query.anim_time*1440*2-120)*-10", "30+math.sin(query.anim_time*1440*2+60)*-5", "math.sin(query.anim_time*1440*2)*-10"],
						"7.6667": [-10, 60, "60+math.sin(query.anim_time*90)*-5"]
					}
				},
				"BackWingRight": {
					"rotation": {
						"0.0": [10, 10, "60+math.sin(query.anim_time*90-90)*-5"],
						"2.8333": [10, 10, "60+math.sin(query.anim_time*90-90)*-5"],
						"3.0": ["math.sin(query.anim_time*1440*2-60)*10", "-20+math.sin(query.anim_time*1440*2+120)*5", "10+math.sin(query.anim_time*1440*2+60)*10"],
						"3.5": ["math.sin(query.anim_time*1440*2-60)*10", "-20+math.sin(query.anim_time*1440*2+120)*5", "10+math.sin(query.anim_time*1440*2+60)*10"],
						"3.6667": [10, 10, "60+math.sin(query.anim_time*90-90)*-5"],
						"6.8333": [10, 10, "60+math.sin(query.anim_time*90-90)*-5"],
						"7.0": ["math.sin(query.anim_time*1440*2-60)*10", "-20+math.sin(query.anim_time*1440*2+120)*5", "10+math.sin(query.anim_time*1440*2+60)*10"],
						"7.5": ["math.sin(query.anim_time*1440*2-60)*10", "-20+math.sin(query.anim_time*1440*2+120)*5", "10+math.sin(query.anim_time*1440*2+60)*10"],
						"7.6667": [10, 10, "60+math.sin(query.anim_time*90-90)*-5"]
					},
					"position": [-0.5, -1, 0]
				},
				"FrontArmRight": {
					"rotation": ["math.sin(query.anim_time*720)*5", -10, 0]
				},
				"BackLegLeft": {
					"rotation": ["10+math.sin(query.anim_time*180)*-2.5", -10, 35]
				},
				"MiddleLegRight": {
					"rotation": ["10+math.sin(query.anim_time*180)*-2.5", 0, -40]
				},
				"BackLegRight": {
					"rotation": ["10+math.sin(query.anim_time*180)*-2.5", 10, -35]
				}
			}
		},
		"animation.kimmeridgebrachypteraeschnidium.preen": {
			"animation_length": 3,
			"bones": {
				"Body": {
					"rotation": {
						"0.0": [0, 0, 0],
						"0.5": [0, 0, 0],
						"0.5833": [-15, 0, 0],
						"0.6667": [-10, 0, 0],
						"2.5": [-10, 0, 0],
						"2.6667": [0, 0, 0],
						"3.0": [0, 0, 0]
					},
					"position": {
						"0.0": [0, -0.25, 0],
						"3.0": [0, -0.25, 0]
					}
				},
				"Butt": {
					"rotation": {
						"0.0": [0, 0, 0],
						"3.0": [0, 0, 0]
					}
				},
				"Head": {
					"rotation": {
						"0.0": [0, 0, 0],
						"0.5": [0, 0, 0],
						"0.5833": [25, 25, 35],
						"0.6667": [20, 20, "30+math.sin(query.anim_time*1440)*5"],
						"1.5": [20, 20, "30+math.sin(query.anim_time*1440)*5"],
						"1.75": [20, -20, "-30+math.sin(query.anim_time*1440)*-5"],
						"2.5": [20, -20, "-30+math.sin(query.anim_time*1440)*-5"],
						"2.6667": [20, 0, 0],
						"2.8333": [20, 0, 0],
						"3.0": [0, 0, 0]
					}
				},
				"FrontWingLeft": {
					"rotation": {
						"0.0": [-10, -60, -10],
						"0.4167": [-10, -60, "-10+math.sin(query.anim_time*90)*5"],
						"0.5": ["math.sin(query.anim_time*1440*2-120)*-10", "-30+math.sin(query.anim_time*1440*2+60)*5", "math.sin(query.anim_time*1440*2)*10"],
						"0.75": [-10, -60, "-10+math.sin(query.anim_time*90)*5"],
						"2.5": [-10, -60, "-10+math.sin(query.anim_time*90)*5"],
						"2.5833": ["math.sin(query.anim_time*1440*2-120)*-10", "-30+math.sin(query.anim_time*1440*2+60)*5", "math.sin(query.anim_time*1440*2)*10"],
						"3.0": [-10, -60, -10]
					}
				},
				"BackWingLeft": {
					"rotation": {
						"0.0": [10, -10, -10],
						"0.4167": [10, -10, "-10+math.sin(query.anim_time*90-90)*5"],
						"0.5": ["math.sin(query.anim_time*1440*2-60)*10", "20+math.sin(query.anim_time*1440*2+120)*-5", "-10+math.sin(query.anim_time*1440*2+60)*-10"],
						"0.75": [10, -10, "-10+math.sin(query.anim_time*90-90)*5"],
						"2.5": [10, -10, "-10+math.sin(query.anim_time*90-90)*5"],
						"2.5833": ["math.sin(query.anim_time*1440*2-60)*10", "20+math.sin(query.anim_time*1440*2+120)*-5", "-10+math.sin(query.anim_time*1440*2+60)*-10"],
						"3.0": [10, -10, -10]
					}
				},
				"FrontArmLeft": {
					"rotation": {
						"0.0": [5, 15, -25],
						"0.3333": [5, 15, -25],
						"0.4167": [-25, -40, -15],
						"0.5": [-20, "-35+math.sin(query.anim_time*1440)*-10", "-10+math.sin(query.anim_time*1440+60)*30"],
						"2.0": [0, -35, 10],
						"2.6667": [5, 15, -25],
						"3.0": [5, 15, -25]
					},
					"scale": {
						"0.0": [1, 1, 1],
						"0.3333": [1, 1, 1],
						"0.4167": [1, 0.8, 1],
						"2.5": [1, 0.8, 1],
						"2.6667": [1, 1, 1],
						"3.0": [1, 1, 1]
					}
				},
				"MiddleLegLeft": {
					"rotation": {
						"0.0": [-15, 15, 0],
						"0.5": [-15, 15, 0],
						"0.5833": [0, 15, 0],
						"0.6667": [-5, 15, 0],
						"2.5": [-5, 15, 0],
						"2.6667": [-15, 15, 0],
						"3.0": [-15, 15, 0]
					}
				},
				"FrontWingRight": {
					"rotation": {
						"0.0": [-10, 60, 10],
						"0.4167": [-10, 60, "10+math.sin(query.anim_time*90)*-5"],
						"0.5": ["math.sin(query.anim_time*1440*2-120)*-10", "30+math.sin(query.anim_time*1440*2+60)*-5", "math.sin(query.anim_time*1440*2)*-10"],
						"0.75": [-10, 60, "10+math.sin(query.anim_time*90)*-5"],
						"2.5": [-10, 60, "10+math.sin(query.anim_time*90)*-5"],
						"2.5833": ["math.sin(query.anim_time*1440*2-120)*-10", "30+math.sin(query.anim_time*1440*2+60)*-5", "math.sin(query.anim_time*1440*2)*-10"],
						"3.0": [-10, 60, 10]
					}
				},
				"BackWingRight": {
					"rotation": {
						"0.0": [10, 10, 10],
						"0.4167": [10, 10, "10+math.sin(query.anim_time*90-90)*-5"],
						"0.5": ["math.sin(query.anim_time*1440*2-60)*10", "-20+math.sin(query.anim_time*1440*2+120)*5", "10+math.sin(query.anim_time*1440*2+60)*10"],
						"0.75": [10, 10, "10+math.sin(query.anim_time*90-90)*-5"],
						"2.5": [10, 10, "10+math.sin(query.anim_time*90-90)*-5"],
						"2.5833": ["math.sin(query.anim_time*1440*2-60)*10", "-20+math.sin(query.anim_time*1440*2+120)*5", "10+math.sin(query.anim_time*1440*2+60)*10"],
						"3.0": [10, 10, 10]
					}
				},
				"FrontArmRight": {
					"rotation": {
						"0.0": [5, -15, 25],
						"0.8333": [5, -15, 25],
						"1.5": [-10, 35, 0],
						"2.5": [-20, "35+math.sin(query.anim_time*1440)*10", "10+math.sin(query.anim_time*1440+60)*-30"],
						"2.6667": [5, -15, 25],
						"3.0": [5, -15, 25]
					},
					"scale": {
						"0.0": [1, 1, 1],
						"0.8333": [1, 1, 1],
						"1.0": [1, 0.8, 1],
						"2.5": [1, 0.8, 1],
						"2.6667": [1, 1, 1],
						"3.0": [1, 1, 1]
					}
				},
				"BackLegLeft": {
					"rotation": {
						"0.0": [15, -20, 0],
						"0.5": [15, -20, 0],
						"0.5833": [35, -10, 0],
						"0.6667": [30, -15, 0],
						"2.5": [30, -15, 0],
						"2.6667": [15, -20, 0],
						"3.0": [15, -20, 0]
					}
				},
				"MiddleLegRight": {
					"rotation": {
						"0.0": [-15, -15, 0],
						"0.5": [-15, -15, 0],
						"0.5833": [0, -15, 0],
						"0.6667": [-5, -15, 0],
						"2.5": [-5, -15, 0],
						"2.6667": [-15, -15, 0],
						"3.0": [-15, -15, 0]
					}
				},
				"BackLegRight": {
					"rotation": {
						"0.0": [15, 20, 0],
						"0.5": [15, 20, 0],
						"0.5833": [35, 10, 0],
						"0.6667": [30, 15, 0],
						"2.5": [30, 15, 0],
						"2.6667": [15, 20, 0],
						"3.0": [15, 20, 0]
					}
				}
			}
		}
	}
}