{
  "text": "ammon.txt",
  "title": "    Ammonite",
  "page_to_go": "unusualprehistory:dinosaurs",
  "recipes": [
    {
      "recipe": "unusualprehistory:ammonite_shell",
      "shapeless": false,
      "x": 210,
      "y": 50,
      "page": 0,
      "scale": 1.3
    },
    {
      "recipe": "unusualprehistory:warpick",
      "shapeless": false,
      "x": 10,
      "y": 70,
      "page": 1,
      "scale": 1.3
    }
  ],
  "entity_renders": [
    {
      "entity": "unusualprehistory:ammon",
      "x": 90,
      "y": 100,
      "page" : 0,
      "scale": 1.5,
      "rot_x": 30,
      "rot_y": 225,
      "rot_z": 0,
      "follow_cursor": false
    }
  ],
  "entity_button":[
    {
      "entity": "unusualprehistory:ammon",
      "x": 290,
      "y": 40,
      "page" : 0,
      "scale": 1.2,
      "entity_scale": 1,
      "offset_x": 1,
      "offset_y": -6,
      "hover_text": "Ammonite"
    }
  ]
}